ApiNyaEr/__init__.py
ApiNyaEr/_req.py
ApiNyaEr/apinya.py
ApiNyaEr/songs.py
ApiNyaEr/td.py
ApiNyaEr/teks.py
apinyaer-2.1.dist-info/LICENSE
apinyaer-2.1.dist-info/METADATA
apinyaer-2.1.dist-info/WHEEL
apinyaer-2.1.dist-info/top_level.txt
apinyaer-2.1.dist-info/RECORD
