Metadata-Version: 2.2
Name: ApiNyaEr
Version: 2.1
Summary: An Api Compile from another source
Author: ErNewDev0
License: GNU General Public License v3.0
Project-URL: Issues, https://github.com/ErRickow/ApiNyaEr/issues
Project-URL: Source, https://pypi.org/projects/ApiNyaEr 
Project-URL: Community, https://t.me/Pamerdong
Project-URL: Documentation, https://docs-apinyaer.rtfd.io
Classifier: Programming Language :: Python :: 3.9
Classifier: Programming Language :: Python :: 3.10
Classifier: Programming Language :: Python :: 3.11
Classifier: Programming Language :: Python :: 3.12
Classifier: License :: OSI Approved :: GNU General Public License v3 (GPLv3)
Requires-Python: >=3.9
License-File: LICENSE
Requires-Dist: aiofiles
Requires-Dist: pillow
Requires-Dist: httpx
Requires-Dist: beautifulsoup4
Requires-Dist: aiohttp
